python_bithumb/__init__.py
python_bithumb/private_api.py
python_bithumb/public_api.py
python_bithumb-0.1.3.dist-info/licenses/LICENSE
python_bithumb-0.1.3.dist-info/METADATA
python_bithumb-0.1.3.dist-info/WHEEL
python_bithumb-0.1.3.dist-info/top_level.txt
python_bithumb-0.1.3.dist-info/RECORD
