Metadata-Version: 2.4
Name: python-bithumb
Version: 0.1.3
Summary: A Python wrapper for Bithumb API
Home-page: https://github.com/youtube-jocoding/python-bithumb
Author: youtube-jocoding
Author-email: business@jocoding.net
License: Apache-2.0
Classifier: Programming Language :: Python :: 3
Classifier: License :: OSI Approved :: Apache Software License
Classifier: Operating System :: OS Independent
Requires-Python: >=3.7
License-File: LICENSE
Requires-Dist: requests>=2.0.0
Requires-Dist: pyjwt>=2.0.0
Requires-Dist: pandas>=1.0.0
Dynamic: author
Dynamic: author-email
Dynamic: classifier
Dynamic: description
Dynamic: description-content-type
Dynamic: home-page
Dynamic: license
Dynamic: license-file
Dynamic: requires-dist
Dynamic: requires-python
Dynamic: summary
